nosqlite/__init__.py
nosqlite/nosqlite.py
json_nosqlite-0.0.6.dist-info/LICENSE
json_nosqlite-0.0.6.dist-info/METADATA
json_nosqlite-0.0.6.dist-info/WHEEL
json_nosqlite-0.0.6.dist-info/top_level.txt
json_nosqlite-0.0.6.dist-info/RECORD
