Metadata-Version: 2.1
Name: json-nosqlite
Version: 0.0.6
Summary: JSON flat file database system
Home-page: https://github.com/chiefbean/nosqlite
Author: chiefbean
Author-email: stevenkarschnia@gmail.com
License: UNKNOWN
Project-URL: Bug Tracker, https://github.com/chiefbean/nosqlite/issues
Platform: UNKNOWN
Classifier: Programming Language :: Python :: 3
Classifier: License :: OSI Approved :: MIT License
Classifier: Operating System :: OS Independent
Requires-Python: >=3.6
License-File: LICENSE
